whisper_lid/__init__.py
whisper_lid/whisper_lid.py
whisper_lid-0.0.1.dist-info/licenses/LICENSE
whisper_lid-0.0.1.dist-info/METADATA
whisper_lid-0.0.1.dist-info/WHEEL
whisper_lid-0.0.1.dist-info/top_level.txt
whisper_lid-0.0.1.dist-info/RECORD
